imgpy/__init__.py
imgpy-1.1.0.dist-info/DESCRIPTION.rst
imgpy-1.1.0.dist-info/METADATA
imgpy-1.1.0.dist-info/RECORD
imgpy-1.1.0.dist-info/WHEEL
imgpy-1.1.0.dist-info/metadata.json
imgpy-1.1.0.dist-info/top_level.txt
