Metadata-Version: 2.0
Name: imgpy
Version: 1.1.0
Summary: Image processing library for Python with animated GIFs support
Home-page: https://github.com/embali/imgpy/
Author: Anton Smolin
Author-email: smolin.anton@gmail.com
License: MIT
Keywords: image info crop resize thumbnail gif
Platform: UNKNOWN
Classifier: Development Status :: 5 - Production/Stable
Classifier: Intended Audience :: Developers
Classifier: License :: OSI Approved :: MIT License
Classifier: Programming Language :: Python :: 3.5
Classifier: Programming Language :: Python :: 3.6
Requires-Dist: Pillow (>=4.1.1)
